<?xml version="1.0" encoding="UTF-8"?>
<xml>
  <file>
    <title>Volume</title>
    <breadcumbs>
      <link file="Objects.html">
        <text>Objects</text>
      </link>
      <text>
        -> <objLink/>
      </text>
      <text>
        -> <propsLink/>
      </text>
      <text>
        -> <propLink/>
      </text>
    </breadcumbs>

    <descriptionarticle only="false">
      <p>
        <text></text>
      </p>
      <p>
        <textAll>
	  This property is used to regulate movie sound level. Accepted values: 0-1000.
It is convenient to link this property with the object <b>Track bar</b> setting 1000 as <b>maximum</b> value for the Track bar property. 
   </textAll>
      </p>
    </descriptionarticle>
    <exceptions>
    </exceptions>

    <remarks>
     
      <text>Values that are less than "0" and more than "3000" are regarded as invalid.</text>
    </remarks>

    <samples>
      <sample lang="Algorithm2">
        <sampletitle></sampletitle>
        <samplecode>
</samplecode>
</sample>
</samples>

    <seealso>
      <est/>
      <li/><li/><propsLink/><br/>
    </seealso>

  </file>
</xml>
